appearonline/__init__.py
appearonline/__main__.py
appearonline/appearonline.py
appearonline-1.0.4.dist-info/LICENSE
appearonline-1.0.4.dist-info/METADATA
appearonline-1.0.4.dist-info/WHEEL
appearonline-1.0.4.dist-info/entry_points.txt
appearonline-1.0.4.dist-info/top_level.txt
appearonline-1.0.4.dist-info/RECORD
