Metadata-Version: 2.1
Name: appearonline
Version: 1.0.4
Summary: Appear Online in Microsoft Teams
Home-page: https://github.com/gansel51/appear-online
Author: Griffin Ansel
Author-email: griffin.ansel@gmail.com
License: MIT
Platform: UNKNOWN
Classifier: Development Status :: 5 - Production/Stable
Classifier: License :: OSI Approved :: MIT License
Classifier: Programming Language :: Python :: 3
Classifier: Programming Language :: Python :: 3.7
Classifier: Topic :: Software Development :: Libraries :: Python Modules
Requires-Dist: pyobjc-framework-Quartz (==7.3)
Requires-Dist: macmouse (==0.7.4) ; platform_system == "Darwin"
Requires-Dist: mouse (==0.7.1) ; platform_system == "Linux"
Requires-Dist: mouse (==0.7.1) ; platform_system == "Windows"
